lusid/__init__.py
lusid/api/__init__.py
lusid/api/abor_api.py
lusid/api/abor_configuration_api.py
lusid/api/address_key_definition_api.py
lusid/api/aggregation_api.py
lusid/api/allocations_api.py
lusid/api/amortisation_rule_sets_api.py
lusid/api/application_metadata_api.py
lusid/api/blocks_api.py
lusid/api/calendars_api.py
lusid/api/chart_of_accounts_api.py
lusid/api/complex_market_data_api.py
lusid/api/compliance_api.py
lusid/api/configuration_recipe_api.py
lusid/api/conventions_api.py
lusid/api/corporate_action_sources_api.py
lusid/api/counterparties_api.py
lusid/api/custom_entities_api.py
lusid/api/custom_entity_definitions_api.py
lusid/api/custom_entity_types_api.py
lusid/api/cut_label_definitions_api.py
lusid/api/data_types_api.py
lusid/api/derived_transaction_portfolios_api.py
lusid/api/entities_api.py
lusid/api/executions_api.py
lusid/api/fee_types_api.py
lusid/api/fund_configuration_api.py
lusid/api/funds_api.py
lusid/api/group_reconciliations_api.py
lusid/api/instrument_event_types_api.py
lusid/api/instrument_events_api.py
lusid/api/instruments_api.py
lusid/api/legacy_compliance_api.py
lusid/api/legal_entities_api.py
lusid/api/order_graph_api.py
lusid/api/order_instructions_api.py
lusid/api/order_management_api.py
lusid/api/orders_api.py
lusid/api/packages_api.py
lusid/api/participations_api.py
lusid/api/persons_api.py
lusid/api/placements_api.py
lusid/api/portfolio_groups_api.py
lusid/api/portfolios_api.py
lusid/api/property_definitions_api.py
lusid/api/queryable_keys_api.py
lusid/api/quotes_api.py
lusid/api/reconciliations_api.py
lusid/api/reference_lists_api.py
lusid/api/reference_portfolio_api.py
lusid/api/relation_definitions_api.py
lusid/api/relations_api.py
lusid/api/relationship_definitions_api.py
lusid/api/relationships_api.py
lusid/api/schemas_api.py
lusid/api/scopes_api.py
lusid/api/scripted_translation_api.py
lusid/api/search_api.py
lusid/api/sequences_api.py
lusid/api/staged_modifications_api.py
lusid/api/staging_rule_set_api.py
lusid_sdk-2.1.472.dist-info/METADATA
lusid_sdk-2.1.472.dist-info/WHEEL
lusid_sdk-2.1.472.dist-info/RECORD
