Metadata-Version: 2.1
Name: lusid-sdk
Version: 2.1.472
Summary: LUSID API
Home-page: https://github.com/finbourne/lusid-sdk-python
License: MIT
Keywords: OpenAPI,OpenAPI-Generator,LUSID API,lusid-sdk
Author: FINBOURNE Technology
Author-email: info@finbourne.com
Requires-Python: >=3.8,<4.0
Classifier: License :: OSI Approved :: MIT License
Classifier: Programming Language :: Python :: 3
Classifier: Programming Language :: Python :: 3.8
Classifier: Programming Language :: Python :: 3.9
Classifier: Programming Language :: Python :: 3.10
Classifier: Programming Language :: Python :: 3.11
Classifier: Programming Language :: Python :: 3.12
Requires-Dist: aenum (>=3.1.11,<4.0.0)
Requires-Dist: aiohttp (>=3.8.4,<4.0.0)
Requires-Dist: pydantic (>=2.6.3,<3.0.0)
Requires-Dist: python-dateutil (>=2.8.2,<3.0.0)
Requires-Dist: requests (>=2,<3)
Requires-Dist: urllib3 (>=1.25.3,<2.0.0)
Project-URL: Repository, https://github.com/finbourne/lusid-sdk-python
